setup.py
gotodate/__init__.py
gotodate/gotodate.py
gotodate.egg-info/PKG-INFO
gotodate.egg-info/SOURCES.txt
gotodate.egg-info/dependency_links.txt
gotodate.egg-info/requires.txt
gotodate.egg-info/top_level.txt