Metadata-Version: 1.0
Name: gotodate
Version: 0.1.5
Summary: 获取某天，前N天，后N天，当前日期周几，当前日期所在周的周一至周日日期
Home-page: https://github.com/shancang/pythonlib.git
Author: Shancang Chen
Author-email: chenshancang@163.com
License: UNKNOWN
Platform: any
